db4me/__init__.py
db4me/__version__.py
db4me/connection.py
db4me/connection_tests.py
db4me/errors.py
db4me/settings.py
docs/api.md
docs/index.md
docs/requirements.txt
db4me-0.1.0.dist-info/LICENSE
db4me-0.1.0.dist-info/METADATA
db4me-0.1.0.dist-info/WHEEL
db4me-0.1.0.dist-info/top_level.txt
db4me-0.1.0.dist-info/RECORD
